{
	"info": {
		"_postman_id": "b93e17fd-70fd-45e6-aee5-3700c14dde66",
		"name": "DAN",
		"description": "# 🚀 Get started here\n\nThis template guides you through CRUD operations (GET, POST, PUT, DELETE), variables, and tests.\n\n## 🔖 **How to use this template**\n\n#### **Step 1: Send requests**\n\nRESTful APIs allow you to perform CRUD operations using the POST, GET, PUT, and DELETE HTTP methods.\n\nThis collection contains each of these [request](https://learning.postman.com/docs/sending-requests/requests/) types. Open each request and click \"Send\" to see what happens.\n\n#### **Step 2: View responses**\n\nObserve the response tab for status code (200 OK), response time, and size.\n\n#### **Step 3: Send new Body data**\n\nUpdate or add new data in \"Body\" in the POST request. Typically, Body data is also used in PUT request.\n\n```\n{\n    \"name\": \"Add your name in the body\"\n}\n\n ```\n\n#### **Step 4: Update the variable**\n\nVariables enable you to store and reuse values in Postman. We have created a [variable](https://learning.postman.com/docs/sending-requests/variables/) called `base_url` with the sample request [https://postman-api-learner.glitch.me](https://postman-api-learner.glitch.me). Replace it with your API endpoint to customize this collection.\n\n#### **Step 5: Add tests in the \"Tests\" tab**\n\nTests help you confirm that your API is working as expected. You can write test scripts in JavaScript and view the output in the \"Test Results\" tab.\n\n<img src=\"https://content.pstmn.io/b5f280a7-4b09-48ec-857f-0a7ed99d7ef8/U2NyZWVuc2hvdCAyMDIzLTAzLTI3IGF0IDkuNDcuMjggUE0ucG5n\">\n\n## 💪 Pro tips\n\n- Use folders to group related requests and organize the collection.\n    \n- Add more [scripts](https://learning.postman.com/docs/writing-scripts/intro-to-scripts/) in \"Tests\" to verify if the API works as expected and execute workflows.\n    \n\n## 💡Related templates\n\n[API testing basics](https://go.postman.co/redirect/workspace?type=personal&collectionTemplateId=e9a37a28-055b-49cd-8c7e-97494a21eb54&sourceTemplateId=ddb19591-3097-41cf-82af-c84273e56719)  \n[API documentation](https://go.postman.co/redirect/workspace?type=personal&collectionTemplateId=e9c28f47-1253-44af-a2f3-20dce4da1f18&sourceTemplateId=ddb19591-3097-41cf-82af-c84273e56719)  \n[Authorization methods](https://go.postman.co/redirect/workspace?type=personal&collectionTemplateId=31a9a6ed-4cdf-4ced-984c-d12c9aec1c27&sourceTemplateId=ddb19591-3097-41cf-82af-c84273e56719)",
		"schema": "https://schema.getpostman.com/json/collection/v2.1.0/collection.json",
		"_exporter_id": "9624087",
		"_collection_link": "https://solar-shadow-554871.postman.co/workspace/My-Workspace~eea3c625-fe52-4e5e-868a-adfc3b15197d/collection/9624087-b93e17fd-70fd-45e6-aee5-3700c14dde66?action=share&source=collection_link&creator=9624087"
	},
	"item": [
		{
			"name": "Auth",
			"item": [
				{
					"name": "Admin",
					"item": [
						{
							"name": "Admin Login",
							"request": {
								"method": "POST",
								"header": [],
								"body": {
									"mode": "raw",
									"raw": "{\r\n    \"email\": \"admin@test.com\",\r\n    \"password\": \"password\"\r\n}",
									"options": {
										"raw": {
											"language": "json"
										}
									}
								},
								"url": {
									"raw": "http://localhost:3000/api/auth/admin/login",
									"protocol": "http",
									"host": [
										"localhost"
									],
									"port": "3000",
									"path": [
										"api",
										"auth",
										"admin",
										"login"
									]
								}
							},
							"response": []
						},
						{
							"name": "Admin Profile",
							"protocolProfileBehavior": {
								"disableBodyPruning": true
							},
							"request": {
								"auth": {
									"type": "bearer",
									"bearer": [
										{
											"key": "token",
											"value": "",
											"type": "string"
										}
									]
								},
								"method": "GET",
								"header": [],
								"body": {
									"mode": "graphql",
									"graphql": {
										"query": "",
										"variables": ""
									}
								},
								"url": {
									"raw": "http://localhost:3000/api/auth/profile",
									"protocol": "http",
									"host": [
										"localhost"
									],
									"port": "3000",
									"path": [
										"api",
										"auth",
										"profile"
									]
								}
							},
							"response": []
						},
						{
							"name": "Admin Logout",
							"request": {
								"method": "POST",
								"header": [],
								"url": {
									"raw": "http://localhost:3000/api/auth/logout",
									"protocol": "http",
									"host": [
										"localhost"
									],
									"port": "3000",
									"path": [
										"api",
										"auth",
										"logout"
									]
								}
							},
							"response": []
						}
					]
				},
				{
					"name": "Client",
					"item": [
						{
							"name": "Client Login",
							"request": {
								"method": "POST",
								"header": [],
								"body": {
									"mode": "raw",
									"raw": "{\r\n    \"email\": \"admin_client@dan.com\",\r\n    \"password\": \"password\"\r\n}",
									"options": {
										"raw": {
											"language": "json"
										}
									}
								},
								"url": {
									"raw": "http://localhost:3000/api/auth/client/login",
									"protocol": "http",
									"host": [
										"localhost"
									],
									"port": "3000",
									"path": [
										"api",
										"auth",
										"client",
										"login"
									]
								}
							},
							"response": []
						},
						{
							"name": "Client Logout",
							"request": {
								"method": "POST",
								"header": [],
								"url": {
									"raw": "http://localhost:3000/api/auth/logout",
									"protocol": "http",
									"host": [
										"localhost"
									],
									"port": "3000",
									"path": [
										"api",
										"auth",
										"logout"
									]
								}
							},
							"response": []
						},
						{
							"name": "Client Profile",
							"protocolProfileBehavior": {
								"disableBodyPruning": true
							},
							"request": {
								"auth": {
									"type": "bearer",
									"bearer": [
										{
											"key": "token",
											"value": "",
											"type": "string"
										}
									]
								},
								"method": "GET",
								"header": [],
								"body": {
									"mode": "graphql",
									"graphql": {
										"query": "",
										"variables": ""
									}
								},
								"url": {
									"raw": "http://localhost:3000/api/auth/profile",
									"protocol": "http",
									"host": [
										"localhost"
									],
									"port": "3000",
									"path": [
										"api",
										"auth",
										"profile"
									]
								}
							},
							"response": []
						}
					]
				}
			]
		},
		{
			"name": "User",
			"item": [
				{
					"name": "Get all Users",
					"request": {
						"method": "GET",
						"header": [],
						"url": {
							"raw": "http://localhost:3000/api/users",
							"protocol": "http",
							"host": [
								"localhost"
							],
							"port": "3000",
							"path": [
								"api",
								"users"
							]
						}
					},
					"response": []
				},
				{
					"name": "Get Single User",
					"request": {
						"method": "GET",
						"header": [],
						"url": {
							"raw": "http://localhost:3000/api/users/1",
							"protocol": "http",
							"host": [
								"localhost"
							],
							"port": "3000",
							"path": [
								"api",
								"users",
								"1"
							]
						}
					},
					"response": []
				},
				{
					"name": "Create User",
					"request": {
						"method": "POST",
						"header": [],
						"body": {
							"mode": "raw",
							"raw": "{\r\n    \"username\": \"Client888\",\r\n    \"password_hash\": \"password\",\r\n    \"confirm_password_hash\": \"password\",\r\n    \"email\": \"Client888@gmail.com\",\r\n    \"role\": 0\r\n}",
							"options": {
								"raw": {
									"language": "json"
								}
							}
						},
						"url": {
							"raw": "http://localhost:3000/api/users",
							"protocol": "http",
							"host": [
								"localhost"
							],
							"port": "3000",
							"path": [
								"api",
								"users"
							]
						}
					},
					"response": []
				},
				{
					"name": "Update User",
					"request": {
						"method": "PUT",
						"header": [
							{
								"key": "Authorization",
								"value": "Bearer eyJhbGciOiJIUzI1NiIsInR5cCI6IkpXVCJ9.eyJ1c2VyX2lkIjo1LCJyb2xlIjoxLCJpYXQiOjE3MTQwMjIxNjAsImV4cCI6MTcxNDEwODU2MH0.42MyXnj-llSAzPNUIH1Gf6yqRebv5TAlgeS_Zlik2wQ",
								"type": "text"
							}
						],
						"body": {
							"mode": "raw",
							"raw": "{\r\n    \"username\": \"super-Admin\",\r\n    \"email\": \"superadmin@dan.com\",\r\n    \"role\": 1,\r\n    \"password_hash\": \"\",\r\n    \"confirm_password_hash\": \"\"\r\n}",
							"options": {
								"raw": {
									"language": "json"
								}
							}
						},
						"url": {
							"raw": "http://localhost:3000/api/users/5",
							"protocol": "http",
							"host": [
								"localhost"
							],
							"port": "3000",
							"path": [
								"api",
								"users",
								"5"
							]
						}
					},
					"response": []
				},
				{
					"name": "Delete User",
					"request": {
						"method": "DELETE",
						"header": [],
						"url": {
							"raw": "http://localhost:3000/api/users/4",
							"protocol": "http",
							"host": [
								"localhost"
							],
							"port": "3000",
							"path": [
								"api",
								"users",
								"4"
							]
						}
					},
					"response": []
				}
			]
		},
		{
			"name": "Category",
			"item": [
				{
					"name": "Create Category",
					"request": {
						"auth": {
							"type": "bearer",
							"bearer": [
								{
									"key": "token",
									"value": "",
									"type": "string"
								}
							]
						},
						"method": "POST",
						"header": [
							{
								"key": "Authorization",
								"value": "Bearer eyJhbGciOiJIUzI1NiIsInR5cCI6IkpXVCJ9.eyJ1c2VyX2lkIjoxLCJpYXQiOjE3MTI1NjQ1ODYsImV4cCI6MTcxMjY1MDk4Nn0.LwcWiEcBASnKPS3jRNgG1iNkwsPdHQGelDZAnrDzVhk",
								"type": "text"
							}
						],
						"body": {
							"mode": "raw",
							"raw": "\r\n{\r\n    \"name\": \"Category333\"\r\n}",
							"options": {
								"raw": {
									"language": "json"
								}
							}
						},
						"url": {
							"raw": "http://localhost:3000/api/categories",
							"protocol": "http",
							"host": [
								"localhost"
							],
							"port": "3000",
							"path": [
								"api",
								"categories"
							]
						}
					},
					"response": []
				},
				{
					"name": "Get Single Category",
					"protocolProfileBehavior": {
						"disableBodyPruning": true
					},
					"request": {
						"auth": {
							"type": "basic",
							"basic": [
								{
									"key": "password",
									"value": "password",
									"type": "string"
								},
								{
									"key": "username",
									"value": "dan@admin.com",
									"type": "string"
								}
							]
						},
						"method": "GET",
						"header": [],
						"body": {
							"mode": "raw",
							"raw": "",
							"options": {
								"raw": {
									"language": "json"
								}
							}
						},
						"url": {
							"raw": "http://localhost:3000/api/categories/2",
							"protocol": "http",
							"host": [
								"localhost"
							],
							"port": "3000",
							"path": [
								"api",
								"categories",
								"2"
							]
						}
					},
					"response": []
				},
				{
					"name": "Update Category",
					"request": {
						"auth": {
							"type": "bearer",
							"bearer": [
								{
									"key": "token",
									"value": "eyJhbGciOiJIUzI1NiIsInR5cCI6IkpXVCJ9.eyJ1c2VyX2lkIjoxLCJyb2xlIjoyLCJpYXQiOjE3MTI1NjY5MDYsImV4cCI6MTcxMjY1MzMwNn0.74k4kUYXyXMxmSeephjpwNjpxatfIaU1CFUZDseEuis",
									"type": "string"
								}
							]
						},
						"method": "PATCH",
						"header": [
							{
								"key": "Authorization",
								"value": "Bearer eyJhbGciOiJIUzI1NiIsInR5cCI6IkpXVCJ9.eyJ1c2VyX2lkIjoxLCJyb2xlIjoyLCJpYXQiOjE3MTI1NjY5MDYsImV4cCI6MTcxMjY1MzMwNn0.74k4kUYXyXMxmSeephjpwNjpxatfIaU1CFUZDseEuis",
								"type": "text"
							}
						],
						"body": {
							"mode": "raw",
							"raw": "{\r\n    \"name\": \"Catgory777\"\r\n}",
							"options": {
								"raw": {
									"language": "json"
								}
							}
						},
						"url": {
							"raw": "http://localhost:3000/api/categories/2",
							"protocol": "http",
							"host": [
								"localhost"
							],
							"port": "3000",
							"path": [
								"api",
								"categories",
								"2"
							]
						}
					},
					"response": []
				},
				{
					"name": "Delete Category",
					"request": {
						"method": "DELETE",
						"header": [],
						"body": {
							"mode": "raw",
							"raw": "",
							"options": {
								"raw": {
									"language": "json"
								}
							}
						},
						"url": {
							"raw": "http://localhost:3000/api/categories/1",
							"protocol": "http",
							"host": [
								"localhost"
							],
							"port": "3000",
							"path": [
								"api",
								"categories",
								"1"
							]
						}
					},
					"response": []
				},
				{
					"name": "Get All Categories",
					"request": {
						"auth": {
							"type": "bearer",
							"bearer": [
								{
									"key": "token",
									"value": "eyJhbGciOiJIUzI1NiIsInR5cCI6IkpXVCJ9.eyJ1c2VyX2lkIjoxLCJyb2xlIjoyLCJpYXQiOjE3MTI1NjY5MDYsImV4cCI6MTcxMjY1MzMwNn0.74k4kUYXyXMxmSeephjpwNjpxatfIaU1CFUZDseEuis",
									"type": "string"
								}
							]
						},
						"method": "GET",
						"header": [
							{
								"key": "Authorization",
								"value": "Bearer eyJhbGciOiJIUzI1NiIsInR5cCI6IkpXVCJ9.eyJ1c2VyX2lkIjoxLCJyb2xlIjoyLCJpYXQiOjE3MTI1NjY5MDYsImV4cCI6MTcxMjY1MzMwNn0.74k4kUYXyXMxmSeephjpwNjpxatfIaU1CFUZDseEuis",
								"type": "text"
							}
						],
						"url": {
							"raw": "http://localhost:3000/api/categories",
							"protocol": "http",
							"host": [
								"localhost"
							],
							"port": "3000",
							"path": [
								"api",
								"categories"
							]
						}
					},
					"response": []
				},
				{
					"name": "Delete All Categories",
					"request": {
						"method": "DELETE",
						"header": [],
						"url": {
							"raw": "http://localhost:3000/api/categories",
							"protocol": "http",
							"host": [
								"localhost"
							],
							"port": "3000",
							"path": [
								"api",
								"categories"
							]
						}
					},
					"response": []
				}
			]
		},
		{
			"name": "Account",
			"item": [
				{
					"name": "User Information",
					"event": [
						{
							"listen": "prerequest",
							"script": {
								"exec": [
									""
								],
								"type": "text/javascript",
								"packages": {}
							}
						}
					],
					"protocolProfileBehavior": {
						"disableBodyPruning": true
					},
					"request": {
						"method": "GET",
						"header": [],
						"body": {
							"mode": "file",
							"file": {}
						},
						"url": {
							"raw": "http://localhost:3000/api/account",
							"protocol": "http",
							"host": [
								"localhost"
							],
							"port": "3000",
							"path": [
								"api",
								"account"
							]
						}
					},
					"response": []
				},
				{
					"name": "Change User Password",
					"event": [
						{
							"listen": "prerequest",
							"script": {
								"exec": [
									""
								],
								"type": "text/javascript",
								"packages": {}
							}
						}
					],
					"request": {
						"auth": {
							"type": "bearer",
							"bearer": [
								{
									"key": "token",
									"value": "",
									"type": "string"
								}
							]
						},
						"method": "PATCH",
						"header": [
							{
								"key": "Content-Type",
								"value": "application/json",
								"type": "text",
								"disabled": true
							}
						],
						"body": {
							"mode": "urlencoded",
							"urlencoded": [
								{
									"key": "old_password",
									"value": "aaaaaaa",
									"type": "text"
								},
								{
									"key": "new_password",
									"value": "admin12345",
									"type": "text"
								},
								{
									"key": "confirm_new_password",
									"value": "admin123",
									"type": "text"
								}
							]
						},
						"url": {
							"raw": "http://localhost:3000/api/account",
							"protocol": "http",
							"host": [
								"localhost"
							],
							"port": "3000",
							"path": [
								"api",
								"account"
							]
						}
					},
					"response": []
				}
			]
		},
		{
			"name": "Customer",
			"item": [
				{
					"name": "Get all Customers",
					"request": {
						"method": "GET",
						"header": [],
						"url": {
							"raw": "http://localhost:3000/api/customers",
							"protocol": "http",
							"host": [
								"localhost"
							],
							"port": "3000",
							"path": [
								"api",
								"customers"
							]
						}
					},
					"response": []
				},
				{
					"name": "Create Customer",
					"request": {
						"method": "POST",
						"header": [],
						"body": {
							"mode": "raw",
							"raw": "{\r\n    \"company_name\": \"Test Company\",\r\n    \"company_name_kana\": \"テスト\",\r\n    \"username\": \"API Tester\",\r\n    \"phone\": \"123-4567-8900\",\r\n    \"email\": \"test@test.com\",\r\n    \"line_flag\": 0,\r\n    \"memo\": \"This is test memo.\"\r\n}",
							"options": {
								"raw": {
									"language": "json"
								}
							}
						},
						"url": {
							"raw": "http://localhost:3000/api/customers",
							"protocol": "http",
							"host": [
								"localhost"
							],
							"port": "3000",
							"path": [
								"api",
								"customers"
							]
						}
					},
					"response": []
				},
				{
					"name": "Get Single Customer",
					"request": {
						"method": "GET",
						"header": [],
						"url": {
							"raw": "http://localhost:3000/api/customers/175",
							"protocol": "http",
							"host": [
								"localhost"
							],
							"port": "3000",
							"path": [
								"api",
								"customers",
								"175"
							]
						}
					},
					"response": []
				},
				{
					"name": "Update Customer",
					"request": {
						"method": "PUT",
						"header": [],
						"body": {
							"mode": "raw",
							"raw": "{\r\n    \"company_name\": \"Test Company1234\",\r\n    \"company_name_kana\": \"テスト\",\r\n    \"username\": \"API Tester\",\r\n    \"phone\": \"123-4567-8900\",\r\n    \"email\": \"test@test.com\",\r\n    \"line_flag\": 0,\r\n    \"memo\": \"This is test memo123.\"\r\n}",
							"options": {
								"raw": {
									"language": "json"
								}
							}
						},
						"url": {
							"raw": "http://localhost:3000/api/customers/175",
							"protocol": "http",
							"host": [
								"localhost"
							],
							"port": "3000",
							"path": [
								"api",
								"customers",
								"175"
							]
						}
					},
					"response": []
				},
				{
					"name": "Delete Customer",
					"request": {
						"method": "DELETE",
						"header": [],
						"url": {
							"raw": "http://localhost:3000/api/customers/175",
							"protocol": "http",
							"host": [
								"localhost"
							],
							"port": "3000",
							"path": [
								"api",
								"customers",
								"175"
							]
						}
					},
					"response": []
				}
			]
		},
		{
			"name": "Application",
			"item": [
				{
					"name": "Get All Applications",
					"request": {
						"method": "GET",
						"header": [],
						"url": {
							"raw": "http://localhost:3000/api/applications",
							"protocol": "http",
							"host": [
								"localhost"
							],
							"port": "3000",
							"path": [
								"api",
								"applications"
							]
						}
					},
					"response": []
				},
				{
					"name": "Get Single Application",
					"request": {
						"method": "GET",
						"header": [],
						"url": {
							"raw": "http://localhost:3000/api/applications/57",
							"protocol": "http",
							"host": [
								"localhost"
							],
							"port": "3000",
							"path": [
								"api",
								"applications",
								"57"
							]
						}
					},
					"response": []
				},
				{
					"name": "Create New Application",
					"request": {
						"method": "POST",
						"header": [],
						"body": {
							"mode": "raw",
							"raw": "{\r\n    \"form_id\": 14,\r\n    \"application_name\": \"Application test2\",\r\n    \"application_name_kana\": \"テスト\",\r\n    \"customer_id\": 171,\r\n    \"staff_user_id\": 1,\r\n    \"deadline\": \"2024-09-25\",\r\n    \"notification_weeks\": 0,\r\n    \"notification_days\": 0\r\n}",
							"options": {
								"raw": {
									"language": "json"
								}
							}
						},
						"url": {
							"raw": "http://localhost:3000/api/applications",
							"protocol": "http",
							"host": [
								"localhost"
							],
							"port": "3000",
							"path": [
								"api",
								"applications"
							]
						}
					},
					"response": []
				},
				{
					"name": "Update Application",
					"request": {
						"method": "PUT",
						"header": [],
						"body": {
							"mode": "raw",
							"raw": "{\r\n    \"application_name\": \"Application test\"\r\n}",
							"options": {
								"raw": {
									"language": "json"
								}
							}
						},
						"url": {
							"raw": "http://localhost:3000/api/applications/57",
							"protocol": "http",
							"host": [
								"localhost"
							],
							"port": "3000",
							"path": [
								"api",
								"applications",
								"57"
							]
						}
					},
					"response": []
				},
				{
					"name": "Delete Application",
					"request": {
						"method": "DELETE",
						"header": [],
						"url": {
							"raw": "http://localhost:3000/api/applications/58",
							"protocol": "http",
							"host": [
								"localhost"
							],
							"port": "3000",
							"path": [
								"api",
								"applications",
								"58"
							]
						}
					},
					"response": []
				},
				{
					"name": "Application Top Page",
					"protocolProfileBehavior": {
						"disableBodyPruning": true
					},
					"request": {
						"method": "GET",
						"header": [],
						"body": {
							"mode": "formdata",
							"formdata": []
						},
						"url": {
							"raw": "http://localhost:3000/api/applications/top-page",
							"protocol": "http",
							"host": [
								"localhost"
							],
							"port": "3000",
							"path": [
								"api",
								"applications",
								"top-page"
							]
						}
					},
					"response": []
				},
				{
					"name": "Create Application Comment",
					"request": {
						"method": "POST",
						"header": [],
						"body": {
							"mode": "raw",
							"raw": "{\r\n    \"content\": \"This is test comment for application 59.\"\r\n}",
							"options": {
								"raw": {
									"language": "json"
								}
							}
						},
						"url": {
							"raw": "http://localhost:3000/api/applications/59/comments",
							"protocol": "http",
							"host": [
								"localhost"
							],
							"port": "3000",
							"path": [
								"api",
								"applications",
								"59",
								"comments"
							]
						}
					},
					"response": []
				},
				{
					"name": "Download Application",
					"request": {
						"method": "GET",
						"header": [],
						"url": {
							"raw": "http://localhost:3000/api/applications/59/download",
							"protocol": "http",
							"host": [
								"localhost"
							],
							"port": "3000",
							"path": [
								"api",
								"applications",
								"59",
								"download"
							]
						}
					},
					"response": []
				}
			]
		},
		{
			"name": "Application Form Field",
			"item": [
				{
					"name": "Get All Application Form Fields",
					"request": {
						"method": "GET",
						"header": [],
						"url": {
							"raw": "http://localhost:3000/api/application-form-fields",
							"protocol": "http",
							"host": [
								"localhost"
							],
							"port": "3000",
							"path": [
								"api",
								"application-form-fields"
							]
						}
					},
					"response": []
				},
				{
					"name": "Get Single Application Form Field",
					"request": {
						"method": "GET",
						"header": [],
						"url": {
							"raw": "http://localhost:3000/api/application-form-fields/114",
							"protocol": "http",
							"host": [
								"localhost"
							],
							"port": "3000",
							"path": [
								"api",
								"application-form-fields",
								"114"
							]
						}
					},
					"response": []
				},
				{
					"name": "Create Application Form Field",
					"request": {
						"method": "POST",
						"header": [],
						"body": {
							"mode": "formdata",
							"formdata": [
								{
									"key": "application_id",
									"value": "59",
									"type": "text"
								},
								{
									"key": "document_name",
									"value": "New Document 999",
									"type": "text"
								},
								{
									"key": "description",
									"value": "This is description 999.",
									"type": "text"
								},
								{
									"key": "required",
									"value": "0",
									"type": "text"
								},
								{
									"key": "file",
									"type": "file",
									"src": "/C:/Users/otama/Downloads/TestData/Lorem Ipsum.pdf"
								}
							]
						},
						"url": {
							"raw": "http://localhost:3000/api/application-form-fields",
							"protocol": "http",
							"host": [
								"localhost"
							],
							"port": "3000",
							"path": [
								"api",
								"application-form-fields"
							]
						}
					},
					"response": []
				},
				{
					"name": "Update Application Form Field Document",
					"request": {
						"method": "PUT",
						"header": [],
						"body": {
							"mode": "formdata",
							"formdata": [
								{
									"key": "is_delete_file",
									"value": "111",
									"type": "text"
								},
								{
									"key": "file",
									"type": "file",
									"src": "/C:/Users/otama/Downloads/TestData/Lorem Ipsum.pdf"
								}
							]
						},
						"url": {
							"raw": "http://localhost:3000/api/application-form-fields/114/documents",
							"protocol": "http",
							"host": [
								"localhost"
							],
							"port": "3000",
							"path": [
								"api",
								"application-form-fields",
								"114",
								"documents"
							]
						}
					},
					"response": []
				},
				{
					"name": "Delete Application Form Field Document",
					"request": {
						"method": "DELETE",
						"header": [],
						"url": {
							"raw": "http://localhost:3000/api/application-form-fields/114/documents",
							"protocol": "http",
							"host": [
								"localhost"
							],
							"port": "3000",
							"path": [
								"api",
								"application-form-fields",
								"114",
								"documents"
							]
						}
					},
					"response": []
				},
				{
					"name": "Update Application Form Field Submission",
					"request": {
						"method": "PUT",
						"header": [],
						"body": {
							"mode": "formdata",
							"formdata": [
								{
									"key": "is_delete_file",
									"value": "123",
									"type": "text"
								},
								{
									"key": "file",
									"type": "file",
									"src": "/C:/Users/otama/Downloads/TestData/test.xlsx"
								}
							]
						},
						"url": {
							"raw": "http://localhost:3000/api/application-form-fields/114/submissions",
							"protocol": "http",
							"host": [
								"localhost"
							],
							"port": "3000",
							"path": [
								"api",
								"application-form-fields",
								"114",
								"submissions"
							]
						}
					},
					"response": []
				},
				{
					"name": "Delete Application Form Field",
					"request": {
						"method": "DELETE",
						"header": [],
						"url": {
							"raw": "http://localhost:3000/api/application-form-fields/114",
							"protocol": "http",
							"host": [
								"localhost"
							],
							"port": "3000",
							"path": [
								"api",
								"application-form-fields",
								"114"
							]
						}
					},
					"response": []
				},
				{
					"name": "Download Application Form Field Document",
					"protocolProfileBehavior": {
						"disableBodyPruning": true
					},
					"request": {
						"method": "GET",
						"header": [],
						"body": {
							"mode": "formdata",
							"formdata": []
						},
						"url": {
							"raw": "http://localhost:3000/api/application-form-fields/115/download/documents?is_new=1",
							"protocol": "http",
							"host": [
								"localhost"
							],
							"port": "3000",
							"path": [
								"api",
								"application-form-fields",
								"115",
								"download",
								"documents"
							],
							"query": [
								{
									"key": "is_new",
									"value": "1"
								}
							]
						}
					},
					"response": []
				},
				{
					"name": "Download Application Form Field Submission",
					"request": {
						"method": "GET",
						"header": [],
						"url": {
							"raw": "http://localhost:3000/api/application-form-fields/114/download/submissions",
							"protocol": "http",
							"host": [
								"localhost"
							],
							"port": "3000",
							"path": [
								"api",
								"application-form-fields",
								"114",
								"download",
								"submissions"
							]
						}
					},
					"response": []
				}
			]
		},
		{
			"name": "Comment",
			"item": [
				{
					"name": "Get All Comments",
					"request": {
						"method": "GET",
						"header": [],
						"url": {
							"raw": "http://localhost:3000/api/comments",
							"protocol": "http",
							"host": [
								"localhost"
							],
							"port": "3000",
							"path": [
								"api",
								"comments"
							]
						}
					},
					"response": []
				},
				{
					"name": "Create A New Comment",
					"request": {
						"method": "POST",
						"header": [],
						"body": {
							"mode": "raw",
							"raw": "{\r\n    \"content\": \"This is test content.\",\r\n    \"application_id\": \"57\",\r\n    \"user_id\": \"197\",\r\n    \"sender\": \"1\"\r\n}",
							"options": {
								"raw": {
									"language": "json"
								}
							}
						},
						"url": {
							"raw": "http://localhost:3000/api/comments",
							"protocol": "http",
							"host": [
								"localhost"
							],
							"port": "3000",
							"path": [
								"api",
								"comments"
							]
						}
					},
					"response": []
				},
				{
					"name": "Get A Single Comment",
					"request": {
						"method": "GET",
						"header": [],
						"url": {
							"raw": "http://localhost:3000/api/comments/55",
							"protocol": "http",
							"host": [
								"localhost"
							],
							"port": "3000",
							"path": [
								"api",
								"comments",
								"55"
							]
						}
					},
					"response": []
				},
				{
					"name": "Update Comment",
					"request": {
						"method": "PATCH",
						"header": [],
						"body": {
							"mode": "raw",
							"raw": "{\r\n    \"content\": \"This is test content123.\"\r\n}",
							"options": {
								"raw": {
									"language": "json"
								}
							}
						},
						"url": {
							"raw": "http://localhost:3000/api/comments/55",
							"protocol": "http",
							"host": [
								"localhost"
							],
							"port": "3000",
							"path": [
								"api",
								"comments",
								"55"
							]
						}
					},
					"response": []
				},
				{
					"name": "Delete Comment",
					"request": {
						"method": "DELETE",
						"header": [],
						"url": {
							"raw": "http://localhost:3000/api/comments/54",
							"protocol": "http",
							"host": [
								"localhost"
							],
							"port": "3000",
							"path": [
								"api",
								"comments",
								"54"
							]
						}
					},
					"response": []
				}
			]
		},
		{
			"name": "Notification",
			"item": [
				{
					"name": "Get All Notifications",
					"request": {
						"method": "GET",
						"header": [],
						"url": {
							"raw": "http://localhost:3000/api/notifications",
							"protocol": "http",
							"host": [
								"localhost"
							],
							"port": "3000",
							"path": [
								"api",
								"notifications"
							]
						}
					},
					"response": []
				},
				{
					"name": "Get A Single Notification",
					"request": {
						"method": "GET",
						"header": [],
						"url": {
							"raw": "http://localhost:3000/api/notifications/1",
							"protocol": "http",
							"host": [
								"localhost"
							],
							"port": "3000",
							"path": [
								"api",
								"notifications",
								"1"
							]
						}
					},
					"response": []
				},
				{
					"name": "Create A Notification",
					"request": {
						"method": "POST",
						"header": [],
						"body": {
							"mode": "raw",
							"raw": "",
							"options": {
								"raw": {
									"language": "json"
								}
							}
						},
						"url": {
							"raw": "http://localhost:3000/api/notifications",
							"protocol": "http",
							"host": [
								"localhost"
							],
							"port": "3000",
							"path": [
								"api",
								"notifications"
							]
						}
					},
					"response": []
				},
				{
					"name": "Update Notification",
					"request": {
						"method": "PATCH",
						"header": [],
						"url": {
							"raw": "http://localhost:3000/api/notifications/1",
							"protocol": "http",
							"host": [
								"localhost"
							],
							"port": "3000",
							"path": [
								"api",
								"notifications",
								"1"
							]
						}
					},
					"response": []
				},
				{
					"name": "Delete Notification",
					"request": {
						"method": "DELETE",
						"header": [],
						"url": {
							"raw": "http://localhost:3000/api/notifications/1",
							"protocol": "http",
							"host": [
								"localhost"
							],
							"port": "3000",
							"path": [
								"api",
								"notifications",
								"1"
							]
						}
					},
					"response": []
				}
			],
			"description": "All the CRUD operation on this table will be performed from another table."
		},
		{
			"name": "Form",
			"item": [
				{
					"name": "Get All Forms",
					"request": {
						"method": "GET",
						"header": [],
						"url": {
							"raw": "http://localhost:3000/api/forms",
							"protocol": "http",
							"host": [
								"localhost"
							],
							"port": "3000",
							"path": [
								"api",
								"forms"
							]
						}
					},
					"response": []
				},
				{
					"name": "Get Single Form",
					"request": {
						"method": "GET",
						"header": [],
						"url": {
							"raw": "http://localhost:3000/api/forms/14",
							"protocol": "http",
							"host": [
								"localhost"
							],
							"port": "3000",
							"path": [
								"api",
								"forms",
								"14"
							]
						}
					},
					"response": []
				},
				{
					"name": "Create a New Form",
					"request": {
						"method": "POST",
						"header": [],
						"body": {
							"mode": "raw",
							"raw": "{\r\n    \"form_name\": \"Form Test11\",\r\n    \"template_id\": \"13\",\r\n    \"category_id\": \"8\",\r\n    \"description\": \"This is form description.\",\r\n    \"form_fields\": [\r\n        {\r\n            \"document_name\": \"Test Document\",\r\n            \"description\": \"This is test description\",\r\n            \"idx\": \"111\",\r\n            \"required\": \"222\"\r\n        }\r\n    ]\r\n}",
							"options": {
								"raw": {
									"language": "json"
								}
							}
						},
						"url": {
							"raw": "http://localhost:3000/api/forms",
							"protocol": "http",
							"host": [
								"localhost"
							],
							"port": "3000",
							"path": [
								"api",
								"forms"
							]
						}
					},
					"response": []
				},
				{
					"name": "Update Form",
					"request": {
						"method": "PUT",
						"header": [],
						"body": {
							"mode": "raw",
							"raw": "{\r\n    \"form_name\": \"test\"\r\n}",
							"options": {
								"raw": {
									"language": "json"
								}
							}
						},
						"url": {
							"raw": "http://localhost:3000/api/forms/14",
							"protocol": "http",
							"host": [
								"localhost"
							],
							"port": "3000",
							"path": [
								"api",
								"forms",
								"14"
							]
						}
					},
					"response": []
				},
				{
					"name": "Delete Form",
					"request": {
						"method": "DELETE",
						"header": [],
						"url": {
							"raw": "http://localhost:3000/api/forms/19",
							"protocol": "http",
							"host": [
								"localhost"
							],
							"port": "3000",
							"path": [
								"api",
								"forms",
								"19"
							]
						}
					},
					"response": []
				},
				{
					"name": "Publish Forms",
					"request": {
						"method": "GET",
						"header": [],
						"url": {
							"raw": "http://localhost:3000/api/forms/publish",
							"protocol": "http",
							"host": [
								"localhost"
							],
							"port": "3000",
							"path": [
								"api",
								"forms",
								"publish"
							]
						}
					},
					"response": []
				}
			]
		},
		{
			"name": "Form Template",
			"item": [
				{
					"name": "Get All Form Templates",
					"request": {
						"method": "GET",
						"header": [],
						"url": {
							"raw": "http://localhost:3000/api/form_templates",
							"protocol": "http",
							"host": [
								"localhost"
							],
							"port": "3000",
							"path": [
								"api",
								"form_templates"
							]
						}
					},
					"response": []
				},
				{
					"name": "Get Single Form Template",
					"request": {
						"method": "GET",
						"header": [],
						"url": {
							"raw": "http://localhost:3000/api/form_templates/8",
							"protocol": "http",
							"host": [
								"localhost"
							],
							"port": "3000",
							"path": [
								"api",
								"form_templates",
								"8"
							]
						}
					},
					"response": []
				},
				{
					"name": "Create A New Form Template",
					"request": {
						"method": "POST",
						"header": [],
						"body": {
							"mode": "raw",
							"raw": "{\r\n    \"template_name\": \"Test Template123\",\r\n    \"category_id\": \"8\",\r\n    \"draft_flag\": \"1\",\r\n    \"form_template_fields\": [\r\n        {\r\n            \"document_name\": \"Test Template Document\",\r\n            \"description\": \"This is template description.\",\r\n            \"required\": 1,\r\n            \"idx\": \"222\",\r\n            \"sample_file_copy\": \"uft1234567890\"\r\n        }\r\n    ]\r\n}",
							"options": {
								"raw": {
									"language": "json"
								}
							}
						},
						"url": {
							"raw": "http://localhost:3000/api/form_templates",
							"protocol": "http",
							"host": [
								"localhost"
							],
							"port": "3000",
							"path": [
								"api",
								"form_templates"
							]
						}
					},
					"response": []
				},
				{
					"name": "Update Form Template",
					"request": {
						"method": "PUT",
						"header": [],
						"body": {
							"mode": "raw",
							"raw": "{\r\n    \"template_name\": \"template_name12345\",\r\n    \"form_template_fields\": [\r\n        {\r\n            \"document_name\": \"Test Template Document12345\",\r\n            \"idx\": \"2\",\r\n            \"is_delete_file\": 1,\r\n            \"description\": \"This is form template field description.\"\r\n        }\r\n    ]\r\n}",
							"options": {
								"raw": {
									"language": "json"
								}
							}
						},
						"url": {
							"raw": "http://localhost:3000/api/form_templates/8",
							"protocol": "http",
							"host": [
								"localhost"
							],
							"port": "3000",
							"path": [
								"api",
								"form_templates",
								"8"
							]
						}
					},
					"response": []
				},
				{
					"name": "Delete Form Template",
					"request": {
						"method": "DELETE",
						"header": [],
						"url": {
							"raw": "http://localhost:3000/api/form_templates/8",
							"protocol": "http",
							"host": [
								"localhost"
							],
							"port": "3000",
							"path": [
								"api",
								"form_templates",
								"8"
							]
						}
					},
					"response": []
				}
			],
			"description": "The operation on form_templates table also stores, updates and deletes data for form_template_fields table."
		},
		{
			"name": "Form Template Field",
			"item": [
				{
					"name": "Get All Form Template Fields",
					"request": {
						"method": "GET",
						"header": [],
						"url": {
							"raw": "http://localhost:3000/api/form-template-fields",
							"protocol": "http",
							"host": [
								"localhost"
							],
							"port": "3000",
							"path": [
								"api",
								"form-template-fields"
							]
						}
					},
					"response": []
				},
				{
					"name": "Get Single Form Template Field",
					"request": {
						"method": "GET",
						"header": [],
						"url": {
							"raw": "http://localhost:3000/api/form-template-fields/1",
							"protocol": "http",
							"host": [
								"localhost"
							],
							"port": "3000",
							"path": [
								"api",
								"form-template-fields",
								"1"
							]
						}
					},
					"response": []
				}
			]
		},
		{
			"name": "Form-Field",
			"item": [
				{
					"name": "Get  All Form-Fields",
					"request": {
						"method": "GET",
						"header": [],
						"url": {
							"raw": "http://localhost:3000/api/form-fields",
							"protocol": "http",
							"host": [
								"localhost"
							],
							"port": "3000",
							"path": [
								"api",
								"form-fields"
							]
						}
					},
					"response": []
				},
				{
					"name": "Get Single Form-Field",
					"request": {
						"method": "GET",
						"header": [],
						"url": {
							"raw": "http://localhost:3000/api/form-fields/48",
							"protocol": "http",
							"host": [
								"localhost"
							],
							"port": "3000",
							"path": [
								"api",
								"form-fields",
								"48"
							]
						}
					},
					"response": []
				},
				{
					"name": "Update Form-Field",
					"request": {
						"method": "PATCH",
						"header": [],
						"body": {
							"mode": "raw",
							"raw": "{\r\n    \"is_delete_file\": 123\r\n}",
							"options": {
								"raw": {
									"language": "json"
								}
							}
						},
						"url": {
							"raw": "http://localhost:3000/api/form-fields/1",
							"protocol": "http",
							"host": [
								"localhost"
							],
							"port": "3000",
							"path": [
								"api",
								"form-fields",
								"1"
							]
						}
					},
					"response": []
				},
				{
					"name": "Create Form-Field",
					"request": {
						"method": "POST",
						"header": [],
						"body": {
							"mode": "raw",
							"raw": "{\r\n    \"document_name\": \"Document Name test\",\r\n    \"description\": \"This is the description\",\r\n    \"idx\": \"222\",\r\n    \"required\": \"111\"\r\n}",
							"options": {
								"raw": {
									"language": "json"
								}
							}
						},
						"url": {
							"raw": "http://localhost:3000/api/form-fields",
							"protocol": "http",
							"host": [
								"localhost"
							],
							"port": "3000",
							"path": [
								"api",
								"form-fields"
							]
						}
					},
					"response": []
				},
				{
					"name": "Delete Form-Field",
					"request": {
						"method": "DELETE",
						"header": [],
						"url": {
							"raw": "http://localhost:3000/api/form-fields/1",
							"protocol": "http",
							"host": [
								"localhost"
							],
							"port": "3000",
							"path": [
								"api",
								"form-fields",
								"1"
							]
						}
					},
					"response": []
				}
			]
		},
		{
			"name": "Line",
			"item": [
				{
					"name": "Admin Line User",
					"item": [
						{
							"name": "Create Admin Line User",
							"request": {
								"method": "POST",
								"header": [],
								"body": {
									"mode": "raw",
									"raw": "{\r\n    \"email\": \"admin@test.com\",\r\n    \"password\": \"password\",\r\n    \"channel_user_id\": \"Ud71ff131f78563cc857e4a1210800242\",\r\n    \"nonce\": \"22222\"\r\n}",
									"options": {
										"raw": {
											"language": "json"
										}
									}
								},
								"url": {
									"raw": "http://localhost:3000/api/auth/admin/line-login",
									"protocol": "http",
									"host": [
										"localhost"
									],
									"port": "3000",
									"path": [
										"api",
										"auth",
										"admin",
										"line-login"
									]
								}
							},
							"response": []
						}
					]
				},
				{
					"name": "Client Line User",
					"item": [
						{
							"name": "Create Client Line User",
							"request": {
								"method": "POST",
								"header": [],
								"body": {
									"mode": "raw",
									"raw": "{\r\n    \"email\": \"admin_client@dan.com\",\r\n    \"password\": \"password\",\r\n    \"channel_user_id\": \"Ud71ff131f78563cc857e4a1210800264\",\r\n    \"nonce\": \"11111\"\r\n}",
									"options": {
										"raw": {
											"language": "json"
										}
									}
								},
								"url": {
									"raw": "http://localhost:3000/api/auth/client/line-login",
									"protocol": "http",
									"host": [
										"localhost"
									],
									"port": "3000",
									"path": [
										"api",
										"auth",
										"client",
										"line-login"
									]
								}
							},
							"response": []
						}
					]
				},
				{
					"name": "Get All Line Users",
					"request": {
						"method": "GET",
						"header": [],
						"url": {
							"raw": "http://localhost:3000/api/line/users",
							"protocol": "http",
							"host": [
								"localhost"
							],
							"port": "3000",
							"path": [
								"api",
								"line",
								"users"
							]
						}
					},
					"response": []
				},
				{
					"name": "Create Line User",
					"request": {
						"method": "POST",
						"header": [],
						"body": {
							"mode": "raw",
							"raw": "{\r\n    \"user_id\": 196,\r\n    \"channel_user_id\": \"Ud71ff131f78563cc857e4a1210800264\"\r\n}",
							"options": {
								"raw": {
									"language": "json"
								}
							}
						},
						"url": {
							"raw": "http://localhost:3000/api/line/user",
							"protocol": "http",
							"host": [
								"localhost"
							],
							"port": "3000",
							"path": [
								"api",
								"line",
								"user"
							]
						}
					},
					"response": []
				},
				{
					"name": "Get Single Line User",
					"request": {
						"method": "GET",
						"header": [],
						"url": {
							"raw": "http://localhost:3000/api/line/user/160",
							"protocol": "http",
							"host": [
								"localhost"
							],
							"port": "3000",
							"path": [
								"api",
								"line",
								"user",
								"160"
							]
						}
					},
					"response": []
				},
				{
					"name": "Line User Detail With ChannelUserID",
					"request": {
						"method": "GET",
						"header": [],
						"url": {
							"raw": "http://localhost:3000/api/line/channel/Ud71ff131f78563cc857e4a1210800362",
							"protocol": "http",
							"host": [
								"localhost"
							],
							"port": "3000",
							"path": [
								"api",
								"line",
								"channel",
								"Ud71ff131f78563cc857e4a1210800362"
							]
						}
					},
					"response": []
				},
				{
					"name": "Delete Line User with ChannelUserID",
					"request": {
						"method": "DELETE",
						"header": [],
						"url": {
							"raw": "http://localhost:3000/api/line/channel/Ud71ff131f78563cc857e4a1210800362",
							"protocol": "http",
							"host": [
								"localhost"
							],
							"port": "3000",
							"path": [
								"api",
								"line",
								"channel",
								"Ud71ff131f78563cc857e4a1210800362"
							]
						}
					},
					"response": []
				}
			]
		},
		{
			"name": "Data Seeder",
			"item": [
				{
					"name": "Data Seeder",
					"request": {
						"method": "GET",
						"header": [],
						"url": {
							"raw": "http://localhost:3000/api/data-seeder",
							"protocol": "http",
							"host": [
								"localhost"
							],
							"port": "3000",
							"path": [
								"api",
								"data-seeder"
							]
						}
					},
					"response": []
				},
				{
					"name": "Template Data Seeder",
					"request": {
						"method": "GET",
						"header": [],
						"url": {
							"raw": "http://localhost:3000/api/data-seeder/template",
							"protocol": "http",
							"host": [
								"localhost"
							],
							"port": "3000",
							"path": [
								"api",
								"data-seeder",
								"template"
							]
						}
					},
					"response": []
				},
				{
					"name": "Application Data Seeder",
					"request": {
						"method": "GET",
						"header": [],
						"url": {
							"raw": "http://localhost:3000/api/data-seeder/applications",
							"protocol": "http",
							"host": [
								"localhost"
							],
							"port": "3000",
							"path": [
								"api",
								"data-seeder",
								"applications"
							]
						}
					},
					"response": []
				}
			]
		},
		{
			"name": "Client",
			"item": [
				{
					"name": "Application",
					"item": [
						{
							"name": "Get All Client Applications",
							"request": {
								"method": "GET",
								"header": [],
								"url": {
									"raw": "http://localhost:3000/api/client/applications",
									"protocol": "http",
									"host": [
										"localhost"
									],
									"port": "3000",
									"path": [
										"api",
										"client",
										"applications"
									]
								}
							},
							"response": []
						},
						{
							"name": "Create Client Application",
							"request": {
								"method": "POST",
								"header": [],
								"body": {
									"mode": "raw",
									"raw": "{\r\n    \"form_id\": 40,\r\n    \"application_name\" : \"Test Application\",\r\n    \"application_name_kana\": \"アプリケーションテスト\",\r\n    \"customer_id\": 175,\r\n    \"staff_user_id\": 198,\r\n    \"deadline\": \"2015/09/22\",\r\n    \"notification_weeks\": 1,\r\n    \"notification_days\": 6\r\n}",
									"options": {
										"raw": {
											"language": "json"
										}
									}
								},
								"url": {
									"raw": "http://localhost:3000/api/client/applications",
									"protocol": "http",
									"host": [
										"localhost"
									],
									"port": "3000",
									"path": [
										"api",
										"client",
										"applications"
									]
								}
							},
							"response": []
						},
						{
							"name": "Get Single Client Application",
							"request": {
								"method": "GET",
								"header": [],
								"url": {
									"raw": "http://localhost:3000/api/client/applications/61",
									"protocol": "http",
									"host": [
										"localhost"
									],
									"port": "3000",
									"path": [
										"api",
										"client",
										"applications",
										"61"
									]
								}
							},
							"response": []
						},
						{
							"name": "Update Client Application",
							"request": {
								"method": "PUT",
								"header": [],
								"body": {
									"mode": "raw",
									"raw": "{\r\n    \"application_name\": \"Test Application 123\"\r\n}",
									"options": {
										"raw": {
											"language": "json"
										}
									}
								},
								"url": {
									"raw": "http://localhost:3000/api/client/applications/61",
									"protocol": "http",
									"host": [
										"localhost"
									],
									"port": "3000",
									"path": [
										"api",
										"client",
										"applications",
										"61"
									]
								}
							},
							"response": []
						},
						{
							"name": "Delete Client Application",
							"request": {
								"method": "DELETE",
								"header": [],
								"url": {
									"raw": "http://localhost:3000/api/client/applications/62",
									"protocol": "http",
									"host": [
										"localhost"
									],
									"port": "3000",
									"path": [
										"api",
										"client",
										"applications",
										"62"
									]
								}
							},
							"response": []
						},
						{
							"name": "Client Application Comment",
							"request": {
								"method": "POST",
								"header": [],
								"body": {
									"mode": "raw",
									"raw": "{\r\n    \"content\": \"This is 3rd client application comment.\"\r\n}",
									"options": {
										"raw": {
											"language": "json"
										}
									}
								},
								"url": {
									"raw": "http://localhost:3000/api/client/applications/61/comments",
									"protocol": "http",
									"host": [
										"localhost"
									],
									"port": "3000",
									"path": [
										"api",
										"client",
										"applications",
										"61",
										"comments"
									]
								}
							},
							"response": []
						},
						{
							"name": "Download Client Application",
							"request": {
								"method": "GET",
								"header": [],
								"url": {
									"raw": "http://localhost:3000/api/client/applications/61/download",
									"protocol": "http",
									"host": [
										"localhost"
									],
									"port": "3000",
									"path": [
										"api",
										"client",
										"applications",
										"61",
										"download"
									]
								}
							},
							"response": []
						},
						{
							"name": "Client Application Top Page",
							"request": {
								"method": "GET",
								"header": [],
								"url": {
									"raw": "http://localhost:3000/api/client/applications/top-page?order_by=deadline&direction=ASC",
									"protocol": "http",
									"host": [
										"localhost"
									],
									"port": "3000",
									"path": [
										"api",
										"client",
										"applications",
										"top-page"
									],
									"query": [
										{
											"key": "order_by",
											"value": "deadline"
										},
										{
											"key": "direction",
											"value": "ASC"
										}
									]
								}
							},
							"response": []
						}
					]
				},
				{
					"name": "Application Form Field",
					"item": [
						{
							"name": "Get All Application Form Fields",
							"request": {
								"method": "GET",
								"header": [],
								"url": {
									"raw": "http://localhost:3000/api/client/application-form-fields",
									"protocol": "http",
									"host": [
										"localhost"
									],
									"port": "3000",
									"path": [
										"api",
										"client",
										"application-form-fields"
									]
								}
							},
							"response": []
						},
						{
							"name": "Create Application Form Field",
							"request": {
								"method": "POST",
								"header": [],
								"body": {
									"mode": "raw",
									"raw": "{\r\n    \"application_id\": \"61\",\r\n    \"document_name\": \"Client Application Form Field\",\r\n    \"description\": \"This is test Application form field description.\",\r\n    \"required\": \"0\"\r\n}",
									"options": {
										"raw": {
											"language": "json"
										}
									}
								},
								"url": {
									"raw": "http://localhost:3000/api/client/application-form-fields",
									"protocol": "http",
									"host": [
										"localhost"
									],
									"port": "3000",
									"path": [
										"api",
										"client",
										"application-form-fields"
									]
								}
							},
							"response": []
						},
						{
							"name": "Get Single Application Form Field",
							"request": {
								"method": "GET",
								"header": [],
								"url": {
									"raw": "http://localhost:3000/api/client/application-form-fields/119",
									"protocol": "http",
									"host": [
										"localhost"
									],
									"port": "3000",
									"path": [
										"api",
										"client",
										"application-form-fields",
										"119"
									]
								}
							},
							"response": []
						},
						{
							"name": "Delete Application Form Field Document",
							"request": {
								"method": "DELETE",
								"header": [],
								"url": {
									"raw": "http://localhost:3000/api/client/application-form-fields/119/documents",
									"protocol": "http",
									"host": [
										"localhost"
									],
									"port": "3000",
									"path": [
										"api",
										"client",
										"application-form-fields",
										"119",
										"documents"
									]
								}
							},
							"response": []
						},
						{
							"name": "Download Application Form Field Document",
							"request": {
								"method": "GET",
								"header": [],
								"url": {
									"raw": "http://localhost:3000/api/client/application-form-fields/119/download/documents",
									"protocol": "http",
									"host": [
										"localhost"
									],
									"port": "3000",
									"path": [
										"api",
										"client",
										"application-form-fields",
										"119",
										"download",
										"documents"
									]
								}
							},
							"response": []
						}
					]
				}
			]
		}
	],
	"event": [
		{
			"listen": "prerequest",
			"script": {
				"type": "text/javascript",
				"exec": [
					""
				]
			}
		},
		{
			"listen": "test",
			"script": {
				"type": "text/javascript",
				"exec": [
					""
				]
			}
		}
	],
	"variable": [
		{
			"key": "id",
			"value": "1"
		},
		{
			"key": "base_url",
			"value": "http://localhost:3000/"
		}
	]
}